finometerdl/__init__.py
finometerdl/logger.py
finometerdl-0.1.2.dist-info/METADATA
finometerdl-0.1.2.dist-info/WHEEL
finometerdl-0.1.2.dist-info/RECORD
