Metadata-Version: 2.1
Name: finometerdl
Version: 0.1.2
Summary: A data logger for the Finometer Medical Device
Home-page: https://github.com/abdrysdale/finometer-data-logger
License: GPL-3.0-or-later
Author: Alex
Author-email: adrysdale@protonmail.com
Requires-Python: >=3.10,<4.0
Classifier: License :: OSI Approved :: GNU General Public License v3 or later (GPLv3+)
Classifier: Programming Language :: Python :: 3
Classifier: Programming Language :: Python :: 3.10
Classifier: Programming Language :: Python :: 3.11
Requires-Dist: pyserial (>=3.5,<4.0)
Project-URL: Repository, https://github.com/abdrysdale/finometer-data-logger
